README.md
setup.py
goatherd/__init__.py
goatherd/constants.py
goatherd/data.yaml
goatherd/engine.py
goatherd/goatherd.py
goatherd/objects.py
goatherd/run_gui.py
goatherd/run_random.py
goatherd/worldgen.py
goatherd.egg-info/PKG-INFO
goatherd.egg-info/SOURCES.txt
goatherd.egg-info/dependency_links.txt
goatherd.egg-info/entry_points.txt
goatherd.egg-info/requires.txt
goatherd.egg-info/top_level.txt
goatherd/assets/1.png
goatherd/assets/2.png
goatherd/assets/3.png
goatherd/assets/4.png
goatherd/assets/5.png
goatherd/assets/arrow-down.png
goatherd/assets/arrow-left.png
goatherd/assets/arrow-right.png
goatherd/assets/arrow-up.png
goatherd/assets/coal.png
goatherd/assets/cow-molken.png
goatherd/assets/cow.png
goatherd/assets/diamond.png
goatherd/assets/fence.png
goatherd/assets/furnace.png
goatherd/assets/grass.png
goatherd/assets/heart.png
goatherd/assets/infinity.png
goatherd/assets/iron.png
goatherd/assets/iron_pickaxe.png
goatherd/assets/iron_sword.png
goatherd/assets/lava.png
goatherd/assets/leaves.png
goatherd/assets/log.png
goatherd/assets/milk.png
goatherd/assets/path.png
goatherd/assets/player-down.png
goatherd/assets/player-left.png
goatherd/assets/player-right.png
goatherd/assets/player-up.png
goatherd/assets/player.png
goatherd/assets/sand.png
goatherd/assets/skeleton.png
goatherd/assets/stone.png
goatherd/assets/stone_pickaxe.png
goatherd/assets/stone_sword.png
goatherd/assets/table.png
goatherd/assets/tree.png
goatherd/assets/unknown.png
goatherd/assets/water.png
goatherd/assets/wood.png
goatherd/assets/wood_pickaxe.png
goatherd/assets/wood_sword.png
goatherd/assets/zombie.png